axial_attention/__init__.py
axial_attention/axial_attention.py
axial_attention/reversible.py
axial_attention-0.6.1.dist-info/LICENSE
axial_attention-0.6.1.dist-info/METADATA
axial_attention-0.6.1.dist-info/WHEEL
axial_attention-0.6.1.dist-info/top_level.txt
axial_attention-0.6.1.dist-info/RECORD
