Metadata-Version: 2.1
Name: axial-attention
Version: 0.6.1
Summary: Axial Attention
Home-page: https://github.com/lucidrains/axial-attention
Author: Phil Wang
Author-email: lucidrains@gmail.com
License: MIT
Keywords: attention,artificial intelligence
Platform: UNKNOWN
Classifier: Development Status :: 4 - Beta
Classifier: Intended Audience :: Developers
Classifier: Topic :: Scientific/Engineering :: Artificial Intelligence
Classifier: License :: OSI Approved :: MIT License
Classifier: Programming Language :: Python :: 3.6
Requires-Dist: torch
